[
  {
    "ContainingType": "Mouts.Challenge.Api.Controllers.SalesController",
    "Method": "Create",
    "RelativePath": "api/Sales",
    "HttpMethod": "POST",
    "IsController": true,
    "Order": 0,
    "Parameters": [
      {
        "Name": "command",
        "Type": "Mouts.Challenge.Application.Sales.Commands.CreateSale.CreateSaleCommand",
        "IsRequired": true
      }
    ],
    "ReturnTypes": []
  },
  {
    "ContainingType": "Mouts.Challenge.Api.Controllers.SalesController",
    "Method": "GetAll",
    "RelativePath": "api/Sales",
    "HttpMethod": "GET",
    "IsController": true,
    "Order": 0,
    "Parameters": [],
    "ReturnTypes": []
  },
  {
    "ContainingType": "Mouts.Challenge.Api.Controllers.SalesController",
    "Method": "GetById",
    "RelativePath": "api/Sales/{id}",
    "HttpMethod": "GET",
    "IsController": true,
    "Order": 0,
    "Parameters": [
      {
        "Name": "id",
        "Type": "System.Int32",
        "IsRequired": true
      }
    ],
    "ReturnTypes": []
  },
  {
    "ContainingType": "Mouts.Challenge.Api.Controllers.SalesController",
    "Method": "Update",
    "RelativePath": "api/Sales/{id}",
    "HttpMethod": "PUT",
    "IsController": true,
    "Order": 0,
    "Parameters": [
      {
        "Name": "id",
        "Type": "System.Int32",
        "IsRequired": true
      },
      {
        "Name": "command",
        "Type": "Mouts.Challenge.Application.Sales.Commands.UpdateSale.UpdateSaleCommand",
        "IsRequired": true
      }
    ],
    "ReturnTypes": []
  },
  {
    "ContainingType": "Mouts.Challenge.Api.Controllers.SalesController",
    "Method": "Cancel",
    "RelativePath": "api/Sales/{id}",
    "HttpMethod": "DELETE",
    "IsController": true,
    "Order": 0,
    "Parameters": [
      {
        "Name": "id",
        "Type": "System.Int32",
        "IsRequired": true
      }
    ],
    "ReturnTypes": []
  },
  {
    "ContainingType": "Mouts.Challenge.Api.Controllers.SalesController",
    "Method": "CancelItem",
    "RelativePath": "api/Sales/{saleId}/items/{itemId}/cancel",
    "HttpMethod": "PATCH",
    "IsController": true,
    "Order": 0,
    "Parameters": [
      {
        "Name": "saleId",
        "Type": "System.Int32",
        "IsRequired": true
      },
      {
        "Name": "itemId",
        "Type": "System.Int32",
        "IsRequired": true
      }
    ],
    "ReturnTypes": []
  }
]